trulens/apps/llamaindex/__init__.py
trulens/apps/llamaindex/guardrails.py
trulens/apps/llamaindex/llama.py
trulens/apps/llamaindex/py.typed
trulens/apps/llamaindex/tru_llama.py
trulens/apps/llamaindex/tru_llama_workflow.py
trulens_apps_llamaindex-2.5.3.dist-info/METADATA
trulens_apps_llamaindex-2.5.3.dist-info/WHEEL
trulens_apps_llamaindex-2.5.3.dist-info/RECORD
